scopie/__init__.py
scopie/scopie.py
scopie-0.3.0.dist-info/licenses/LICENSE
scopie-0.3.0.dist-info/METADATA
scopie-0.3.0.dist-info/WHEEL
scopie-0.3.0.dist-info/top_level.txt
scopie-0.3.0.dist-info/RECORD
