Metadata-Version: 2.4
Name: scopie
Version: 0.3.0
Summary: Authorization engine providing fine grained access while you control the data. Aimed at being easy to use and implement without overtaking other parts of your system.
Author-email: Ronnie Smith <miniscruff@hey.com>
License-Expression: MIT
Project-URL: Homepage, https://github.com/miniscruff/scopie-py
Project-URL: Documentation, https://github.com/miniscruff/scopie-py
Project-URL: Repository, https://github.com/miniscruff/scopie-py.git
Project-URL: Issues, https://github.com/miniscruff/scopie-py/issues
Project-URL: Changelog, https://github.com/miniscruff/scopie-py/blob/main/CHANGELOG.md
Keywords: authorization
Classifier: Development Status :: 3 - Alpha
Classifier: Intended Audience :: Developers
Classifier: Programming Language :: Python :: 3
Classifier: Programming Language :: Python :: 3.9
Classifier: Programming Language :: Python :: 3.10
Classifier: Programming Language :: Python :: 3.11
Classifier: Programming Language :: Python :: 3.12
Requires-Python: >=3.9
License-File: LICENSE
Dynamic: license-file
